nums/__init__.py
nums/api.py
nums/sklearn.py
nums/core/__init__.py
nums/core/application_manager.py
nums/core/linalg.py
nums/core/settings.py
nums/core/utils.py
nums/core/version.py
nums/core/array/__init__.py
nums/core/array/application.py
nums/core/array/base.py
nums/core/array/blockarray.py
nums/core/array/errors.py
nums/core/array/random.py
nums/core/array/selection.py
nums/core/array/utils.py
nums/core/array/view.py
nums/core/cmds/__init__.py
nums/core/cmds/api_coverage.py
nums/core/compute/__init__.py
nums/core/compute/compute_interface.py
nums/core/compute/compute_manager.py
nums/core/compute/numpy_compute.py
nums/core/grid/__init__.py
nums/core/grid/grid.py
nums/core/storage/__init__.py
nums/core/storage/storage.py
nums/core/storage/utils.py
nums/core/systems/__init__.py
nums/core/systems/filesystem.py
nums/core/systems/system_interface.py
nums/core/systems/systems.py
nums/core/systems/utils.py
nums/experimental/__init__.py
nums/experimental/nums_xgb.py
nums/models/__init__.py
nums/models/glms.py
nums/models/lbfgs.py
nums/numpy/__generate__.py
nums/numpy/__init__.py
nums/numpy/api.py
nums/numpy/fft.py
nums/numpy/linalg.py
nums/numpy/numpy_utils.py
nums/numpy/random.py
nums-0.2.8.dist-info/LICENSE
nums-0.2.8.dist-info/METADATA
nums-0.2.8.dist-info/WHEEL
nums-0.2.8.dist-info/entry_points.txt
nums-0.2.8.dist-info/top_level.txt
nums-0.2.8.dist-info/RECORD
