Metadata-Version: 2.1
Name: nums
Version: 0.2.8
Summary: A numerical computing library for Python that scales.
Home-page: https://github.com/nums-project/nums
License: UNKNOWN
Platform: UNKNOWN
Classifier: Development Status :: 3 - Alpha
Classifier: Intended Audience :: Science/Research
Classifier: Intended Audience :: Developers
Classifier: License :: OSI Approved :: Apache Software License
Classifier: Programming Language :: C
Classifier: Programming Language :: Python
Classifier: Programming Language :: Python :: 3
Classifier: Programming Language :: Python :: 3.7
Classifier: Programming Language :: Python :: 3.8
Classifier: Programming Language :: Python :: 3.9
Classifier: Programming Language :: Python :: 3 :: Only
Classifier: Programming Language :: Python :: Implementation :: CPython
Classifier: Topic :: Software Development
Classifier: Topic :: Scientific/Engineering
Classifier: Typing :: Typed
Classifier: Operating System :: POSIX :: Linux
Requires-Python: <3.10,>=3.6
License-File: LICENSE
Requires-Dist: numpy (<=1.20.0,>1.18.0)
Requires-Dist: ray[default] (<=1.6.0,>=1.5.0)
Requires-Dist: psutil
Requires-Dist: scipy
Requires-Dist: boto3
Requires-Dist: scikit-learn (<=0.24.0,>0.23.0)
Provides-Extra: testing
Requires-Dist: pytest (==6.1.1) ; extra == 'testing'
Requires-Dist: pylint (==2.10.2) ; extra == 'testing'
Requires-Dist: moto (==1.3.16) ; extra == 'testing'
Requires-Dist: coverage (==5.3) ; extra == 'testing'
Requires-Dist: codecov (==2.1.9) ; extra == 'testing'
Requires-Dist: mypy (==0.910) ; extra == 'testing'
Requires-Dist: black (==21.4b0) ; extra == 'testing'
Requires-Dist: tqdm ; extra == 'testing'
Requires-Dist: invoke ; extra == 'testing'
Requires-Dist: modin ; extra == 'testing'
